{
  "project_info": {
    "project_number": "1035733959374",
    "project_id": "rcs445-d65ae",
    "storage_bucket": "rcs445-d65ae.firebasestorage.app"
  },
  "client": [
    {
      "client_info": {
        "mobilesdk_app_id": "1:1035733959374:android:8c249b4a9f398a40fa069f",
        "android_client_info": {
          "package_name": "com.ashakur.authfirebasse"
        }
      },
      "oauth_client": [],
      "api_key": [
        {
          "current_key": "AIzaSyC2pYfnaBKDifw_9eBxWbR9iHbbyxvCkNk"
        }
      ],
      "services": {
        "appinvite_service": {
          "other_platform_oauth_client": []
        }
      }
    }
  ],
  "configuration_version": "1"
}